django_outbox_middleware/__init__.py
django_outbox_middleware/apps.py
django_outbox_middleware/middleware.py
django_outbox_middleware/models.py
django_outbox_middleware/urls.py
django_outbox_middleware/views.py
django_outbox_middleware/migrations/0001_initial.py
django_outbox_middleware/migrations/0002_outboxrequestlog_request_flagged_duplicate.py
django_outbox_middleware/migrations/0003_auto_20170201_2244.py
django_outbox_middleware/migrations/__init__.py
django_outbox_middleware/static/css/django_outbox_middleware.css
django_outbox_middleware/static/js/django_outbox_middleware.js
django_outbox_middleware/templates/django_outbox_middleware/base.html
django_outbox_middleware-0.2.2.dist-info/DESCRIPTION.rst
django_outbox_middleware-0.2.2.dist-info/METADATA
django_outbox_middleware-0.2.2.dist-info/RECORD
django_outbox_middleware-0.2.2.dist-info/WHEEL
django_outbox_middleware-0.2.2.dist-info/metadata.json
django_outbox_middleware-0.2.2.dist-info/top_level.txt
