Metadata-Version: 2.0
Name: django-outbox-middleware
Version: 0.2.2
Summary: Your project description goes here
Home-page: https://github.com/ArtProcessors/django-outbox-middleware
Author: Jacob Haslehurst
Author-email: jacob@artprocessors.net
License: MIT
Keywords: django-outbox-middleware
Platform: UNKNOWN
Classifier: Development Status :: 3 - Alpha
Classifier: Framework :: Django
Classifier: Framework :: Django :: 1.8
Classifier: Framework :: Django :: 1.9
Classifier: Framework :: Django :: 1.10
Classifier: Intended Audience :: Developers
Classifier: License :: OSI Approved :: BSD License
Classifier: Natural Language :: English
Classifier: Programming Language :: Python :: 2
Classifier: Programming Language :: Python :: 2.7
Classifier: Programming Language :: Python :: 3
Classifier: Programming Language :: Python :: 3.3
Classifier: Programming Language :: Python :: 3.4
Classifier: Programming Language :: Python :: 3.5
Requires-Dist: django-model-utils (>=2.0)
